setup.py
bojs/__init__.py
bojs.egg-info/PKG-INFO
bojs.egg-info/SOURCES.txt
bojs.egg-info/dependency_links.txt
bojs.egg-info/top_level.txt
bojs.egg-info/zip-safe