Metadata-Version: 1.0
Name: bojs
Version: 0.0.0
Summary: bojs: A Sandbox for JavaScript in Python
Home-page: http://github.com/neogeny/bojs
Author: Apalala
Author-email: apalala@gmail.com
License: MIT
Platform: UNKNOWN
